autohedge/__init__.py
autohedge/crypto_agent_wrapper.py
autohedge/e_trade_wrapper.py
autohedge/main.py
autohedge/td_ameritrade.py
autohedge-0.1.0.dist-info/LICENSE
autohedge-0.1.0.dist-info/METADATA
autohedge-0.1.0.dist-info/WHEEL
autohedge-0.1.0.dist-info/RECORD
